google_calendar_fetcher/__init__.py
google_calendar_fetcher/core.py
google_calendar_fetcher-1.0.7.dist-info/LICENSE
google_calendar_fetcher-1.0.7.dist-info/METADATA
google_calendar_fetcher-1.0.7.dist-info/WHEEL
google_calendar_fetcher-1.0.7.dist-info/entry_points.txt
google_calendar_fetcher-1.0.7.dist-info/top_level.txt
google_calendar_fetcher-1.0.7.dist-info/RECORD
